Metadata-Version: 2.4
Name: llama-index-vector-stores-hologres
Version: 0.4.1
Summary: llama-index vector stores hologres integration
Author-email: Your Name <you@example.com>
License-Expression: MIT
License-File: LICENSE
Requires-Python: <4.0,>=3.9
Requires-Dist: hologres-vector==0.0.10
Requires-Dist: llama-index-core<0.15,>=0.13.0
